MANIFEST.in
README.rst
dev.py
setup.py
cli_dev.egg-info/PKG-INFO
cli_dev.egg-info/SOURCES.txt
cli_dev.egg-info/dependency_links.txt
cli_dev.egg-info/entry_points.txt
cli_dev.egg-info/top_level.txt