Metadata-Version: 1.1
Name: cli-dev
Version: 0.1.1
Summary: Register and run a command for each directory
Home-page: https://github.com/eddieantonio/dev
Author: Eddie Antonio Santos
Author-email: easantos@ualberta.ca
License: UNKNOWN
Keywords: testing,shell,cwd
Platform: UNKNOWN
Classifier: Development Status :: 5 - Production/Stable
Classifier: Environment :: Console
Classifier: Intended Audience :: Developers
Classifier: License :: Freely Distributable
Classifier: Operating System :: MacOS :: MacOS X
Classifier: Operating System :: Unix
Classifier: Operating System :: POSIX
Classifier: Programming Language :: Python
Classifier: Programming Language :: Python :: 2.6
Classifier: Programming Language :: Python :: 2.7
Classifier: Topic :: Software Development
Classifier: Topic :: Software Development :: Build Tools
Classifier: Topic :: System :: Systems Administration
